webstarts/__init__.py
webstarts/backend.py
webstarts/defaults.py
webstarts/gunicorn.py
webstarts/log_id.py
webstarts/types.py
webstarts/util.py
webstarts/wflask.py
webstarts/wlog.py
webstarts-2.9.0.dist-info/DESCRIPTION.rst
webstarts-2.9.0.dist-info/METADATA
webstarts-2.9.0.dist-info/RECORD
webstarts-2.9.0.dist-info/WHEEL
webstarts-2.9.0.dist-info/entry_points.txt
webstarts-2.9.0.dist-info/metadata.json
webstarts-2.9.0.dist-info/top_level.txt
webstarts-2.9.0.dist-info/zip-safe
